LICENSE
MANIFEST.in
README.md
setup.py
wscan/__init__.py
wscan/main.py
wscan.egg-info/PKG-INFO
wscan.egg-info/SOURCES.txt
wscan.egg-info/dependency_links.txt
wscan.egg-info/entry_points.txt
wscan.egg-info/requires.txt
wscan.egg-info/top_level.txt
wscan.egg-info/zip-safe
wscan/fuzz/dirList.txt
wscan/fuzz/user_agent.txt
wscan/lib/__init__.py
wscan/lib/controller/Controller.py
wscan/lib/controller/Pages.py
wscan/lib/controller/__init__.py
wscan/lib/exception/ScanException.py
wscan/lib/exception/__init__.py
wscan/lib/io/Argument.py
wscan/lib/io/ColorOutput.py
wscan/lib/io/__init__.py
wscan/lib/tree/DirTree.py
wscan/lib/tree/Node.py
wscan/lib/tree/__init__.py