Metadata-Version: 2.2
Name: wscan
Version: 2.4.6
Summary: A Fast & Simple web site scanner. 
Home-page: https://github.com/testzero-wz/wscan/
Author: T3stzer0
Author-email: testzero.wz@gmail.com
License: MIT
Keywords: wscan scanner fuzz sitemap base on aiohttp
Classifier: License :: OSI Approved :: MIT License
Classifier: Programming Language :: Python :: 3.5
Classifier: Programming Language :: Python :: 3.6
Classifier: Programming Language :: Python :: 3.7
Classifier: Intended Audience :: Developers
License-File: LICENSE
Requires-Dist: aiohttp
Requires-Dist: colorama
Requires-Dist: bs4
Dynamic: author
Dynamic: author-email
Dynamic: classifier
Dynamic: description
Dynamic: description-content-type
Dynamic: home-page
Dynamic: keywords
Dynamic: license
Dynamic: requires-dist
Dynamic: summary
